<annotation>
  <folder>images</folder>
  <filename>498583f14507e34c.jpg</filename>
  <path>drive/MyDrive/data/plate/images/498583f14507e34c.jpg</path>
  <source>
    <database>OpenImages</database>
  </source>
  <size>
    <width>1024</width>
    <height>681</height>
    <depth>3</depth>
  </size>
  <segmented>0</segmented>
  <object>
    <name>plate</name>
    <pose>Unspecified</pose>
    <truncated>0</truncated>
    <difficult>0</difficult>
    <bndbox>
      <xmin>137</xmin>
      <xmax>313</xmax>
      <ymin>349</ymin>
      <ymax>494</ymax>
    </bndbox>
  </object>
  <object>
    <name>plate</name>
    <pose>Unspecified</pose>
    <truncated>0</truncated>
    <difficult>0</difficult>
    <bndbox>
      <xmin>442</xmin>
      <xmax>586</xmax>
      <ymin>197</ymin>
      <ymax>298</ymax>
    </bndbox>
  </object>
</annotation>
